{"version":1,"resource":"file:///home/rafayahmad/Stuff/OOP/lab13/q2.cpp","entries":[{"id":"Ni9w.cpp","timestamp":1714362393145},{"id":"4lR7.cpp","timestamp":1714366520389},{"id":"8xKB.cpp","timestamp":1714366544556},{"id":"MiT2.cpp","timestamp":1714366558323},{"id":"uWno.cpp","timestamp":1714366713497},{"id":"FO31.cpp","timestamp":1714366752618},{"id":"rzDw.cpp","timestamp":1714366792229},{"id":"JDVx.cpp","timestamp":1714366811477},{"id":"ay4A.cpp","timestamp":1714366828234},{"id":"laeB.cpp","timestamp":1714366868551},{"id":"luCp.cpp","timestamp":1714366882979},{"id":"0gZG.cpp","timestamp":1714366924306},{"id":"YAqG.cpp","timestamp":1714366937670},{"id":"wHxh.cpp","timestamp":1714366967724},{"id":"rtll.cpp","timestamp":1714366984251},{"id":"OQdA.cpp","timestamp":1714367009582},{"id":"ScjE.cpp","timestamp":1714367039926},{"id":"d3iJ.cpp","timestamp":1714367118832},{"id":"OqG0.cpp","timestamp":1714367130065},{"id":"PGGx.cpp","timestamp":1714367142572},{"id":"jRaR.cpp","timestamp":1714367164286},{"id":"Mutr.cpp","timestamp":1714367190430},{"id":"LQLL.cpp","timestamp":1714367205252},{"id":"vK7M.cpp","timestamp":1714367264154},{"id":"WJbU.cpp","timestamp":1714367292109},{"id":"RVPf.cpp","timestamp":1714367311944}]}