{"version":1,"resource":"file:///home/rafayahmad/Stuff/Coding/Java/keypress-getter/src/main/java/com/rutils/GlobalKeyListener.java","entries":[{"id":"BHcD.java","source":"Workspace Edit","timestamp":1717060416728},{"id":"06wx.java","source":"renamed.source","timestamp":1717060416953},{"id":"4cji.java","timestamp":1717060431628},{"id":"pugN.java","timestamp":1717060450185},{"id":"9aH8.java","timestamp":1717060465628},{"id":"BkM5.java","timestamp":1717060489998},{"id":"Eu88.java","timestamp":1717060559931},{"id":"Y1jO.java","source":"renamed.source","timestamp":1717060560216},{"id":"o8eV.java","timestamp":1717060569938},{"id":"zEVY.java","timestamp":1717060592142},{"id":"73Eq.java","timestamp":1717060605608},{"id":"MyIv.java","timestamp":1717060619605},{"id":"UBZO.java","timestamp":1717060645968},{"id":"KRWU.java","timestamp":1717060663468},{"id":"dJNO.java","timestamp":1717060702212},{"id":"xP3J.java","timestamp":1717060721608},{"id":"kMXp.java","timestamp":1717060740468},{"id":"7Bf2.java","timestamp":1717060753122},{"id":"K22k.java","timestamp":1717060977943},{"id":"WWQx.java","timestamp":1717061004053},{"id":"7BIl.java","timestamp":1717061280056},{"id":"YP1z.java","timestamp":1717061309739},{"id":"5yQh.java","timestamp":1717061440655},{"id":"X596.java","timestamp":1717061462688},{"id":"bZLJ.java","timestamp":1717061487145},{"id":"7Pge.java","timestamp":1717061497661},{"id":"Nm3P.java","timestamp":1717061515991},{"id":"uNQ6.java","timestamp":1717061530338},{"id":"Cfrz.java","timestamp":1717061720364},{"id":"iI1Q.java","timestamp":1717065454631},{"id":"LNsq.java","timestamp":1717065587584}]}